serietvapi_bot/API_main.py
serietvapi_bot/__init__.py
serietvapi_bot/download_episode.py
serietvapi_bot/music.py
serietvapi_bot-1.1.1.17.dist-info/LICENSE
serietvapi_bot-1.1.1.17.dist-info/METADATA
serietvapi_bot-1.1.1.17.dist-info/WHEEL
serietvapi_bot-1.1.1.17.dist-info/entry_points.txt
serietvapi_bot-1.1.1.17.dist-info/top_level.txt
serietvapi_bot-1.1.1.17.dist-info/RECORD
