Metadata-Version: 2.1
Name: serietvapi-bot
Version: 1.1.1.17
Summary: Un semplice tool Python che si integra con le API del Bot Telegram @SerieTvItaly_bot
Home-page: https://github.com/KingKaitoKid/serietvapi_bot
Author: KingKaitoKid
Author-email: tvditaly@altervista.org
License: UNKNOWN
Platform: UNKNOWN
Classifier: Programming Language :: Python :: 3
Classifier: License :: OSI Approved :: MIT License
Classifier: Operating System :: OS Independent
Requires-Dist: youtube-dl
Requires-Dist: telethon
Requires-Dist: requests
